{
    "id": "token-action-hud-escalation",
    "title": "Token Action HUD Escalation",
    "description": "Escalation (Locked & Loaded) system support for Token Action HUD Core.",
    "version": "1.0.0",
    "compatibility": {
        "minimum": "14",
        "verified": "14"
    },
    "authors": [
        {
            "name": "Mantis"
        }
    ],
    "relationships": {
        "systems": [
            {
                "id": "escalation",
                "type": "system",
                "compatibility": {
                    "minimum": "0.89",
                    "verified": "0.89"
                }
            }
        ],
        "requires": [
            {
                "id": "token-action-hud-core",
                "type": "module",
                "compatibility": {
                    "minimum": "2.1.0",
                    "verified": "2.1.0"
                }
            }
        ]
    },
    "esmodules": [
        "scripts/module.js"
    ]
}
